exdelphi/__init__.py
exdelphi/api_time.py
exdelphi/client.py
exdelphi/data_model.py
exdelphi-0.0.2.dist-info/LICENSE
exdelphi-0.0.2.dist-info/METADATA
exdelphi-0.0.2.dist-info/WHEEL
exdelphi-0.0.2.dist-info/top_level.txt
exdelphi-0.0.2.dist-info/RECORD
