Metadata-Version: 2.1
Name: exdelphi
Version: 0.0.2
Summary: A Python client for the EXDELPHI platform
Author-email: exdelphi <hi@exdelphi.com>
Project-URL: Homepage, https://www.exdelphi.com
Project-URL: Source Code, https://github.com/exdelphi/exdelphi-py
Project-URL: Documentation, https://exdelphi.readthedocs.io/en/latest/
Project-URL: Bug Tracker, https://github.com/exdelphi/exdelphi-py/issues
Classifier: Programming Language :: Python :: 3
Classifier: License :: OSI Approved :: MIT License
Classifier: Operating System :: OS Independent
Requires-Python: >=3.7
License-File: LICENSE
Requires-Dist: pydantic
Requires-Dist: pandas (>=1.0)
Requires-Dist: requests
